obt/__init__.py
obt/_dep_build.py
obt/_dep_build_autoconf.py
obt/_dep_build_bin.py
obt/_dep_build_cmake.py
obt/_dep_build_conan.py
obt/_dep_build_custom.py
obt/_dep_dl.py
obt/_dep_enumerate.py
obt/_dep_fetch.py
obt/_dep_impl.py
obt/_dep_node.py
obt/_dep_provider.py
obt/_dep_x.py
obt/_envutils.py
obt/_globals.py
obt/buildtrace.py
obt/cmake.py
obt/cmake_gen.py
obt/command.py
obt/common.py
obt/conan.py
obt/config.py
obt/cpp_access_analyzer.py
obt/cpp_argparse_v2.py
obt/cpp_class_details.py
obt/cpp_command_base.py
obt/cpp_database_v2.py
obt/cpp_db_files.py
obt/cpp_display_v2.py
obt/cpp_entities_v2.py
obt/cpp_formatter.py
obt/cpp_ingest.py
obt/cpp_inheritance_tree.py
obt/cpp_parser_descent.py
obt/cpp_search_utils.py
obt/cpp_search_v2.py
obt/cpp_stack_analyzer.py
obt/cpp_type_system.py
obt/crypt.py
obt/debug_helpers.py
obt/deco.py
obt/dep.py
obt/docker.py
obt/env.py
obt/executors.py
obt/exeinfo.py
obt/gen_pkgconfig.py
obt/git.py
obt/host.py
obt/libav.py
obt/litex.py
obt/log.py
obt/macos.py
obt/macos_homebrew.py
obt/make.py
obt/manifest.py
obt/misc.py
obt/module.py
obt/net.py
obt/obt_math.py
obt/ork_cppdb.py
obt/osrelease.py
obt/patch.py
obt/path.py
obt/pathtools.py
obt/pip.py
obt/pybind11.py
obt/scp.py
obt/sdk.py
obt/search.py
obt/search_args.py
obt/search_display.py
obt/search_v2.py
obt/subspace.py
obt/target.py
obt/template.py
obt/test_descent_parser.py
obt/tmux.py
obt/utils.py
obt/wget.py
obt/xcode.py
obt/cnc/__init__.py
obt/cnc/saf.py
ork_build-0.0.287.data/data/obt/bin_priv/__init__.py
ork_build-0.0.287.data/data/obt/bin_priv/_obt.test.docker.ssl.client.py
ork_build-0.0.287.data/data/obt/bin_priv/_obt.test.docker.ssl.server.py
ork_build-0.0.287.data/data/obt/bin_priv/_obt_dep_completions.py
ork_build-0.0.287.data/data/obt/bin_priv/_obt_dep_completions_shell.py
ork_build-0.0.287.data/data/obt/bin_priv/_obt_subspace_completions.py
ork_build-0.0.287.data/data/obt/bin_priv/obt.cpp.inhtree.py
ork_build-0.0.287.data/data/obt/bin_priv/obt.cpp.members.py
ork_build-0.0.287.dist-info/METADATA
ork_build-0.0.287.dist-info/WHEEL
ork_build-0.0.287.dist-info/top_level.txt
ork_build-0.0.287.dist-info/RECORD
