Metadata-Version: 2.4
Name: ork.build
Version: 0.0.287
Summary: Orkid Build Tools
Home-page: https://github.com/tweakoz/ork.build
Author: Michael T. Mayers
Author-email: michael@tweakoz.com
Classifier: Programming Language :: Python :: 3
Classifier: License :: OSI Approved :: MIT License
Classifier: Operating System :: OS Independent
Requires-Python: >=3.10
Requires-Dist: yarl
Requires-Dist: toposort
Requires-Dist: os-release
Requires-Dist: distro
Requires-Dist: twine
Requires-Dist: build
Requires-Dist: conan
Requires-Dist: pip>=24.1
Requires-Dist: GitPython
Requires-Dist: libclang
Dynamic: author
Dynamic: author-email
Dynamic: classifier
Dynamic: description
Dynamic: description-content-type
Dynamic: home-page
Dynamic: requires-dist
Dynamic: requires-python
Dynamic: summary
